kognitos/bdk/__version__.py
kognitos/bdk/linter/__init__.py
kognitos/bdk/linter/book/__init__.py
kognitos/bdk/linter/book/book_checker.py
kognitos/bdk/linter/book/book_rule_factory.py
kognitos/bdk/linter/book/rules/__init__.py
kognitos/bdk/linter/book/rules/book_rules.py
kognitos/bdk/linter/concept/__init__.py
kognitos/bdk/linter/concept/concept_checker.py
kognitos/bdk/linter/concept/concept_rule_factory.py
kognitos/bdk/linter/concept/rules/__init__.py
kognitos/bdk/linter/concept/rules/concept_rules.py
kognitos/bdk/linter/config_checker.py
kognitos/bdk/linter/connect/__init__.py
kognitos/bdk/linter/connect/connect_checker.py
kognitos/bdk/linter/connect/connect_rule_factory.py
kognitos/bdk/linter/connect/rules/__init__.py
kognitos/bdk/linter/connect/rules/connect_rule.py
kognitos/bdk/linter/connect/rules/name_rule.py
kognitos/bdk/linter/connect/rules/noun_phrase_rule.py
kognitos/bdk/linter/connect/rules/verify_parameter_rule.py
kognitos/bdk/linter/oauth/__init__.py
kognitos/bdk/linter/oauth/oauth_checker.py
kognitos/bdk/linter/oauth/oauth_rule_factory.py
kognitos/bdk/linter/oauth/rules/__init__.py
kognitos/bdk/linter/oauth/rules/oauth_token_rules.py
kognitos/bdk/linter/procedure/__init__.py
kognitos/bdk/linter/procedure/procedure_checker.py
kognitos/bdk/linter/procedure/procedure_rule_factory.py
kognitos/bdk/linter/procedure/rules/__init__.py
kognitos/bdk/linter/procedure/rules/procedure_rules.py
kognitos/bdk/linter/pyproject_checker.py
kognitos/bdk/linter/register.py
kognitos/bdk/linter/util.py
kognitos_bdk_linter-1.34.0.dist-info/LICENSE
kognitos_bdk_linter-1.34.0.dist-info/METADATA
kognitos_bdk_linter-1.34.0.dist-info/WHEEL
kognitos_bdk_linter-1.34.0.dist-info/entry_points.txt
kognitos_bdk_linter-1.34.0.dist-info/RECORD
