Metadata-Version: 2.1
Name: kognitos-bdk-linter
Version: 1.34.0
Summary: Kognitos BDK Linter
License: Propietary
Author: Emiliano Lesende
Author-email: emiliano@kognitos.com
Requires-Python: >=3.11,<4.0
Classifier: License :: Other/Proprietary License
Classifier: Programming Language :: Python :: 3
Classifier: Programming Language :: Python :: 3.11
Classifier: Programming Language :: Python :: 3.12
Requires-Dist: kognitos-bdk-api (>=1.29)
Requires-Dist: kognitos-bdk-klang (>=2.0.0,<3.0.0)
Requires-Dist: pylint (>=3.0,<4.0)
Requires-Dist: toml (>=0.10.2,<0.11.0)
Requires-Dist: uritemplate (>=4.1.1,<5.0.0)
